GenZ/__init__.py
GenZ/analyse_model.py
GenZ/collective_times.py
GenZ/operator_base.py
GenZ/operators.py
GenZ/parallelism.py
GenZ/system.py
GenZ/unit.py
GenZ/version.py
GenZ/Astra_sim/fix_chakra_traces.py
GenZ/Astra_sim/get_astra_sim_time.py
GenZ/LLM_inference/__init__.py
GenZ/LLM_inference/best_parallelization.py
GenZ/LLM_inference/llm_chunked.py
GenZ/LLM_inference/llm_decode.py
GenZ/LLM_inference/llm_prefill.py
GenZ/LLM_inference/llm_spec_decode.py
GenZ/LLM_inference/platform_size.py
GenZ/LLM_inference/utils.py
GenZ/Models/__init__.py
GenZ/Models/attention.py
GenZ/Models/default_models.py
GenZ/Models/embedding.py
GenZ/Models/ffn.py
GenZ/Models/get_language_model.py
GenZ/Models/mamba.py
GenZ/Models/model_quality.py
GenZ/Models/utils.py
GenZ/Models/Model_sets/alibaba.py
GenZ/Models/Model_sets/google.py
GenZ/Models/Model_sets/meta.py
GenZ/Models/Model_sets/microsoft.py
GenZ/Models/Model_sets/misc.py
GenZ/Models/Model_sets/mistral.py
GenZ/Models/Model_sets/nvidia.py
GenZ/utils/plot_rooflines.py
Systems/system_configs.py
genz_llm-0.0.16.dist-info/licenses/LICENSE
genz_llm-0.0.16.dist-info/METADATA
genz_llm-0.0.16.dist-info/WHEEL
genz_llm-0.0.16.dist-info/top_level.txt
genz_llm-0.0.16.dist-info/RECORD
