Metadata-Version: 2.4
Name: genz_llm
Version: 0.0.16
Summary: GenZ is designed to simplify the relationship between the hardware platform used for serving Large Language Models(LLMs) and inference serving metrics like latency and memory.
Author-email: Abhimanyu Bambhaniya <abambhaniya3@gatech.edu>
Project-URL: Homepage, https://github.com/abhibambhaniya/GenZ-LLM-Analyzer
Project-URL: Issues, https://github.com/abhibambhaniya/GenZ-LLM-Analyzer/issues
Classifier: Programming Language :: Python :: 3
Classifier: License :: OSI Approved :: MIT License
Classifier: Operating System :: OS Independent
Requires-Python: >=3.6
License-File: LICENSE
Requires-Dist: matplotlib>=3.8.0
Requires-Dist: kaleido>=0.2.1
Requires-Dist: nbformat>=5.9.2
Requires-Dist: numpy>=1.26.3
Requires-Dist: pandas>=2.2.1
Requires-Dist: paretoset>=1.2.3
Requires-Dist: pillow>=10.2.0
Requires-Dist: plotly>=5.9.0
Requires-Dist: tqdm>=4.66.2
Requires-Dist: ipywidgets
Requires-Dist: seaborn
Requires-Dist: plotnine
Requires-Dist: Jinja2
Dynamic: license-file
Dynamic: requires-python
